AUTHORS
CMakeLists.txt
CMakeOptions.txt
COPYING
MANIFEST.in
Makefile
README.rst
VERSION
setup.py
docs/README.md
docs/logging.conf.detailed-template
docs/logging.conf.template
docs/simple-pedigree-multiallelic.ped
docs/simple-pedigree.ped
include/.gitignore
include/appinfo.h
include/appinfo.h.in.cmake
include/application.hpp
include/assertion.hpp
include/assumptions.hpp
include/cms_sat_solver_interface.hpp
include/configuration.h
include/configuration.h.in.cmake
include/data.hpp
include/descriptive_class.hpp
include/gender.hpp
include/haplotypes_genotypes.hpp
include/in-pedigree.hpp
include/io-haplotypes_genotypes.hpp
include/io-pedigree.hpp
include/log.hpp
include/ms_sat_solver_interface.hpp
include/out-pedigree.hpp
include/ped2cnf-constraints.hpp
include/ped2cnf.hpp
include/pedcnf.hpp
include/pedcnf2hc.hpp
include/pedigree.hpp
include/rehc_app.hpp
include/sat_solver_interface.hpp
include/timelimit.hpp
include/utility.hpp
reHCstar.egg-info/PKG-INFO
reHCstar.egg-info/SOURCES.txt
reHCstar.egg-info/dependency_links.txt
reHCstar.egg-info/entry_points.txt
reHCstar.egg-info/not-zip-safe
reHCstar.egg-info/pbr.json
reHCstar.egg-info/top_level.txt
rehcstar/__init__.py
rehcstar/reHCstar_mgr.py
solver/CMakeLists.txt
solver/cryptominisat/AUTHORS
solver/cryptominisat/Alg.h
solver/cryptominisat/BitArray.h
solver/cryptominisat/BothCache.cpp
solver/cryptominisat/BothCache.h
solver/cryptominisat/BoundedQueue.h
solver/cryptominisat/CMakeLists.txt
solver/cryptominisat/CSet.h
solver/cryptominisat/Clause.h
solver/cryptominisat/ClauseAllocator.cpp
solver/cryptominisat/ClauseAllocator.h
solver/cryptominisat/ClauseCleaner.cpp
solver/cryptominisat/ClauseCleaner.h
solver/cryptominisat/ClauseOffset.h
solver/cryptominisat/ClauseVivifier.cpp
solver/cryptominisat/ClauseVivifier.h
solver/cryptominisat/CompleteDetachReattacher.cpp
solver/cryptominisat/CompleteDetachReattacher.h
solver/cryptominisat/DataSync.cpp
solver/cryptominisat/DataSync.h
solver/cryptominisat/DimacsParser.cpp
solver/cryptominisat/DimacsParser.h
solver/cryptominisat/DoublePackedRow.h
solver/cryptominisat/FailedLitSearcher.cpp
solver/cryptominisat/FailedLitSearcher.h
solver/cryptominisat/FindUndef.cpp
solver/cryptominisat/FindUndef.h
