Metadata-Version: 1.1
Name: reHCstar
Version: 2.1.5
Summary: A SAT-based program to compute a haplotype configuration on pedigrees with recombinations, genotyping errors, and missing genotypes over biallelic and multi-allelic loci.
Home-page: http://rehcstar.algolab.eu/
Author: Yuri Pirola
Author-email: yuri.pirola@gmail.com
License:                     GNU GENERAL PUBLIC LICENSE
